{
  "bodySnippet": "PDM＋ナレッジ管理 メイン プロジェクト 製品・装置・ユニット 部品 図面管理 文書管理 検索 統合検索 AI検索 類似検索 営業 顧客管理 管理 お知らせ管理 マスタ設定 システム設定 アルパイン 設計事務所 部品一覧 新規登録 検索条件 部品番号 ​ 部品名 ​ カテゴリ ​ ステータス ​ クリア 検索 お気に入りのみ 検索結果 部品番号 部品名 カテゴリ ステータス 担当者 最終更新日 9NG6006A30-00 NOZZLE / ノズルクミ代表部品 test test3 2026/6/1 fgsr fref test test3 創屋 太郎 2026/5/18 P0012 部品12 ワッシャー 下書き アルパイン 設計事務所 2026/5/16 test test test test3 アルパイン 設計事務所 2026/5/11 P0018 部品18 test test3 アルパイン 設計事務所 2026/4/9 P0026 部品26 ワッシャー 試作 アルパイン 設計事務所 2026/3/12 P0014 部品14 test 廃止予定 アルパイン 設計事務所 2026/3",
  "hasAttributeText": false,
  "hasPreviewText": false,
  "hasTagText": false,
  "headers": [
    "部品番号",
    "部品名",
    "カテゴリ",
    "ステータス",
    "担当者",
    "最終更新日"
  ],
  "headings": [
    "PDM＋ナレッジ管理",
    "アルパイン 設計事務所",
    "検索条件",
    "検索結果",
    "部品番号",
    "部品名",
    "カテゴリ"
  ],
  "labels": [
    "PDM＋ナレッジ管理",
    "プロジェクト",
    "製品・装置・ユニット",
    "部品",
    "図面管理",
    "文書管理",
    "統合検索",
    "AI検索",
    "類似検索",
    "顧客管理",
    "お知らせ管理",
    "マスタ設定",
    "システム設定",
    "アルパイン 設計事務所",
    "新規登録",
    "クリア",
    "検索",
    "お気に入りのみ",
    "1",
    "2",
    "3"
  ],
  "title": "ナレッジ",
  "url": "http://210.165.3.139/web/part"
}